pysamsungnasa/__init__.py
pysamsungnasa/__main__.py
pysamsungnasa/autodiscovery.py
pysamsungnasa/cli.py
pysamsungnasa/config.py
pysamsungnasa/helpers.py
pysamsungnasa/nasa.py
pysamsungnasa/nasa_client.py
pysamsungnasa/device/__init__.py
pysamsungnasa/device/controllers.py
pysamsungnasa/pnp/__init__.py
pysamsungnasa/protocol/__init__.py
pysamsungnasa/protocol/enum.py
pysamsungnasa/protocol/parser.py
pysamsungnasa/protocol/factory/__init__.py
pysamsungnasa/protocol/factory/messaging.py
pysamsungnasa/protocol/factory/messages/__init__.py
pysamsungnasa/protocol/factory/messages/indoor.py
pysamsungnasa/protocol/factory/messages/network.py
pysamsungnasa/protocol/factory/messages/outdoor.py
pysamsungnasa-0.5.0.dist-info/licenses/LICENSE
pysamsungnasa-0.5.0.dist-info/WHEEL
pysamsungnasa-0.5.0.dist-info/METADATA
pysamsungnasa-0.5.0.dist-info/RECORD
