Metadata-Version: 2.4
Name: pysamsungnasa
Version: 0.5.0
Summary: Connect to Samsung ASHP / AC units over NASA via RS485
Author-email: Jordan Harvey <jordan@hrvy.uk>
Requires-Python: >=3.13.0
Classifier: Development Status :: 3 - Alpha
Classifier: Intended Audience :: Developers
Classifier: License :: OSI Approved :: MIT License
Classifier: Programming Language :: Python :: 3 :: Only
Classifier: Programming Language :: Python :: 3.13
License-File: LICENSE
Requires-Dist: aiotelnet~=1.1.0
Requires-Dist: prompt_toolkit>=3.0.0 ; extra == "cli"
Requires-Dist: python-dotenv>=0.9.9 ; extra == "cli"
Requires-Dist: mkdocs>=1.4.0 ; extra == "docs"
Requires-Dist: mkdocs-material>=9.0.0 ; extra == "docs"
Requires-Dist: mkdocstrings[python]>=0.23.0 ; extra == "docs"
Requires-Dist: griffe>=0.40 ; extra == "docs"
Requires-Dist: pymdown-extensions>=10.0 ; extra == "docs"
Requires-Dist: bandit[toml]==1.9.2 ; extra == "test"
Requires-Dist: black==25.12.0 ; extra == "test"
Requires-Dist: check-manifest==0.51 ; extra == "test"
Requires-Dist: flake8-bugbear==25.11.29 ; extra == "test"
Requires-Dist: flake8-docstrings ; extra == "test"
Requires-Dist: flake8-formatter_junit_xml ; extra == "test"
Requires-Dist: flake8 ; extra == "test"
Requires-Dist: flake8-pyproject ; extra == "test"
Requires-Dist: pre-commit==4.5.1 ; extra == "test"
Requires-Dist: pylint==4.0.4 ; extra == "test"
Requires-Dist: pylint_junit ; extra == "test"
Requires-Dist: pytest-cov==7.0.0 ; extra == "test"
Requires-Dist: pytest-mock<3.15.2 ; extra == "test"
Requires-Dist: pytest-runner ; extra == "test"
Requires-Dist: pytest-asyncio==1.3.0 ; extra == "test"
Requires-Dist: pytest==9.0.2 ; extra == "test"
Requires-Dist: pytest-github-actions-annotate-failures ; extra == "test"
Requires-Dist: shellcheck-py==0.11.0.1 ; extra == "test"
Project-URL: Documentation, https://github.com/pantherale0/pysamsungnasa
Project-URL: Source, https://github.com/pantherale0/pysamsungnasa
Project-URL: Tracker, https://github.com/pantherale0/pysamsungnasa/issues
Provides-Extra: cli
Provides-Extra: docs
Provides-Extra: test
